LICENSE
README.md
setup.py
commode/__init__.py
commode/common.py
commode/exceptions.py
commode/server.py
commode/types.py
commode.egg-info/PKG-INFO
commode.egg-info/SOURCES.txt
commode.egg-info/dependency_links.txt
commode.egg-info/requires.txt
commode.egg-info/top_level.txt
scripts/commode