Metadata-Version: 2.1
Name: commode
Version: 2.0.0
Summary: Terminal client for Cabinet file server
Author: Magnus Aa. Hirth
Author-email: magnus.hirth@gmail.com
License: UNKNOWN
Platform: UNKNOWN
License-File: LICENSE
